biotorch/__init__.py
biotorch/applications/__init__.py
biotorch/applications/adversarial_attacks/__init__.py
biotorch/applications/adversarial_attacks/functions.py
biotorch/applications/adversarial_attacks/visualization.py
biotorch/autograd/__init__.py
biotorch/autograd/dfa/__init__.py
biotorch/autograd/dfa/conv.py
biotorch/autograd/dfa/linear.py
biotorch/autograd/fa/__init__.py
biotorch/autograd/fa/conv.py
biotorch/autograd/fa/linear.py
biotorch/benchmark/__init__.py
biotorch/benchmark/losses.py
biotorch/benchmark/lr_schedulers.py
biotorch/benchmark/optimizers.py
biotorch/benchmark/run.py
biotorch/datasets/__init__.py
biotorch/datasets/cifar.py
biotorch/datasets/dataset.py
biotorch/datasets/fashion_mnist.py
biotorch/datasets/imagenet.py
biotorch/datasets/mnist.py
biotorch/datasets/selector.py
biotorch/evaluation/__init__.py
biotorch/evaluation/evaluator.py
biotorch/layers/__init__.py
biotorch/layers/metrics.py
biotorch/layers/utils.py
biotorch/layers/backpropagation/__init__.py
biotorch/layers/backpropagation/conv.py
biotorch/layers/backpropagation/linear.py
biotorch/layers/brsf/__init__.py
biotorch/layers/brsf/conv.py
biotorch/layers/brsf/linear.py
biotorch/layers/dfa/__init__.py
biotorch/layers/dfa/conv.py
biotorch/layers/dfa/linear.py
biotorch/layers/fa/__init__.py
biotorch/layers/fa/conv.py
biotorch/layers/fa/linear.py
biotorch/layers/fa_constructor/__init__.py
biotorch/layers/fa_constructor/conv.py
biotorch/layers/fa_constructor/linear.py
biotorch/layers/frsf/__init__.py
biotorch/layers/frsf/conv.py
biotorch/layers/frsf/linear.py
biotorch/layers/usf/__init__.py
biotorch/layers/usf/conv.py
biotorch/layers/usf/linear.py
biotorch/models/__init__.py
biotorch/models/le_net.py
biotorch/models/small_resnet.py
biotorch/models/utils.py
biotorch/models/backpropagation/__init__.py
biotorch/models/backpropagation/alexnet.py
biotorch/models/backpropagation/densenet.py
biotorch/models/backpropagation/le_net.py
biotorch/models/backpropagation/mnasnet.py
biotorch-0.0.1.dist-info/LICENSE
biotorch-0.0.1.dist-info/METADATA
biotorch-0.0.1.dist-info/WHEEL
biotorch-0.0.1.dist-info/top_level.txt
biotorch-0.0.1.dist-info/RECORD
