Metadata-Version: 2.1
Name: biotorch
Version: 0.0.1
Summary: BioTorch is a PyTorch framework specializing in biologically plausible learning algorithms.
Home-page: https://github.com/jsalbert/biotorch
Author: Albert Jimenez
Author-email: albertjimenez@aip.ai
License: UNKNOWN
Platform: UNKNOWN
Requires-Dist: Pillow
Requires-Dist: autoflake
Requires-Dist: autopep8
Requires-Dist: flake8
Requires-Dist: ipykernel
Requires-Dist: jsonschema
Requires-Dist: jupyter
Requires-Dist: matplotlib
Requires-Dist: numpy
Requires-Dist: pandas
Requires-Dist: pep8
Requires-Dist: pytest
Requires-Dist: pytest-cov
Requires-Dist: pyyaml
Requires-Dist: scipy
Requires-Dist: tensorboard
Requires-Dist: torch (>=1.0)
Requires-Dist: torchattacks
Requires-Dist: torchvision
Requires-Dist: tqdm
